FIFO.v
module top #(
    parameter width = 16,
    parameter depth = 32
)(
    input RCLK, LCLK, WRDV, RDEN,
    input [width-1:0] WRDAT,
    output reg F, E,
    output reg [width-1:0] RDDAT
);

	reg [width-1:0] mem [0:depth-1];
	
	reg [5:0] wr_ptr_bin = 0;
    reg [5:0] rd_ptr_bin = 0;
	
	wire [5:0] wr_ptr_grey;
    wire [5:0] rd_ptr_grey;
	
	assign wr_ptr_grey = wr_ptr_bin ^ (wr_ptr_bin >> 1);
	assign rd_ptr_grey = rd_ptr_bin ^ (rd_ptr_bin >> 1);
	
	reg [5:0] wr_ptr_grey_sync_1, wr_ptr_grey_sync_2;
    reg [5:0] rd_ptr_grey_sync_1, rd_ptr_grey_sync_2;
	
	
	// Update the read syncs when LCLK fires and update the write syncs when the RCLK fires
	
	always @(posedge LCLK) begin
		rd_ptr_grey_sync_1 <= rd_ptr_grey;
		rd_ptr_grey_sync_2 <= rd_ptr_grey_sync_1;
	end
	
	always @(posedge RCLK) begin
		wr_ptr_grey_sync_1 <= wr_ptr_grey;
		wr_ptr_grey_sync_2 <= wr_ptr_grey_sync_1;
	end
	
	
	// Write data into the registers of the FIFO memory on the firing of the LCLK given that the source has "Write Valid" and the FIFO is not full
	
	always @(posedge LCLK) begin
		if (WRDV && ~F) begin
			mem[wr_ptr_bin[4:0]] <= WRDAT;
			wr_ptr_bin <= wr_ptr_bin + 1;
		end
	end
	
	// Read data from the registers of the FIFO memory on the firing of the RCLK given that the reader has "Read Enabled" and the FIFO is not empty
	
	always @(posedge RCLK) begin
			if (RDEN && ~E) begin
				RDDAT <= mem[rd_ptr_bin[4:0]];
				rd_ptr_bin <= rd_ptr_bin + 1;
			end
	end
	
	
	// Set the Full and Empty flags as per the read and write pointers
	
	always@(*) begin
		// Full logic : first two MSBs match but the other two match
		F = (wr_ptr_grey == {~rd_ptr_grey_sync_2[5:4], rd_ptr_grey_sync_2[3:0]});
		
		// Empty logic : read pointer equal to write pointer
		E = rd_ptr_grey == wr_ptr_grey_sync_2; 
	end
	
endmodule

FIFO_tb2.v
`timescale 1ns / 1ns
`include "FIFO.v"

module tb_top;

    parameter width = 16;
    parameter depth = 32;

    // Inputs to UUT (reg)
    reg LCLK;
    reg RCLK;
    reg WRDV;
    reg RDEN;
    reg [width-1:0] WRDAT;

    // Outputs from UUT (wire)
    wire F;
    wire E;
    wire [width-1:0] RDDAT;

    // Instantiate UUT (Note: Removed AF/AE since we removed them from your FIFO.v)
    top #(
        .width(width),
        .depth(depth)
    ) uut (
        .LCLK(LCLK),
        .RCLK(RCLK),
        .WRDV(WRDV),
        .RDEN(RDEN),
        .WRDAT(WRDAT),
        .F(F),
        .E(E),
        .RDDAT(RDDAT)
    );

    // 1. Simple, continuous clock generators (using distinct asynchronous speeds)
    always #5 LCLK = (LCLK === 1'b0) ? 1'b1 : 1'b0;
    always #7 RCLK = (RCLK === 1'b0) ? 1'b1 : 1'b0;

    // Helper integer for the manual unrolled generation
    integer idx;

    // 2. Linear Test Sequence
    initial begin
        // Initialize everything strictly to 0
        LCLK  = 0;
        RCLK  = 0;
        WRDV  = 0;
        RDEN  = 0;
        WRDAT = 0;

        // Open wave dump files
        $dumpfile("FIFO_tb.vcd");
        $dumpvars(0, tb_top);
        
        #20; // Let the system settle

        $display("--- STEP 1: FILLING UP THE FIFO COMPLETELY (32 WRITES) ---");

        // We will manually burst 35 items. 
        // The first 32 should succeed, the last 3 should hit the Full flag barrier.
        for (idx = 1; idx <= 35; idx = idx + 1) begin
            WRDAT = idx; // Inject a distinct counter pattern (1, 2, 3...)
            WRDV  = 1;
            #10;         // Hold for 1 LCLK cycle
            WRDV  = 0;
            #10;         // Pause 1 cycle between entries
            
            if (F == 1) begin
                $display("[%0t ns] FIFO Reported FULL at write attempt #%0d!", $time, idx);
            end
        end

        #50; // Give it a breather to let Gray codes synchronize fully

        $display("--- STEP 2: READING OUT 5 WORDS TO FREE UP SPACE ---");
        // Read 5 elements out. This will drop the full flag and advance rd_ptr to 5.
        for (idx = 0; idx < 5; idx = idx + 1) begin
            RDEN = 1;
            #14; // Hold for roughly 1 RCLK cycle
            RDEN = 0;
            $display("[%0t ns] READ SUCCESS: Data popped out = %d", $time, RDDAT);
            #14;
        end

        #50; // Wait for the new read pointer to safely cross the domain border back to LCLK

        $display("--- STEP 3: WRITING AGAIN TO WRAP AROUND (LAP 2) ---");
        // Now address 0, 1, 2, 3, and 4 are empty. 
        // These next writes will overwrite those physical slots.
        
        WRDAT = 16'hAAAA; // Will go into physical memory slot 0
        WRDV  = 1;
        #10;
        WRDV  = 0;
        #10;
        $display("[%0t ns] Wrote AAAA (Wrapping around to slot 0)", $time);

        WRDAT = 16'hBBBB; // Will go into physical memory slot 1
        WRDV  = 1;
        #10;
        WRDV  = 0;
        #10;
        $display("[%0t ns] Wrote BBBB (Wrapping around to slot 1)", $time);

        #50;

        $display("--- Hardcoded Wraparound Test Complete ---");
        $finish;
    end

endmodule

FIFO_tb.vcd
$date
	Mon Jul 20 09:27:25 2026
$end
$version
	Icarus Verilog
$end
$timescale
	1ns
$end
$scope module tb_top $end
$var wire 16 ! RDDAT [15:0] $end
$var wire 1 " F $end
$var wire 1 # E $end
$var parameter 32 $ depth $end
$var parameter 32 % width $end
$var reg 1 & LCLK $end
$var reg 1 ' RCLK $end
$var reg 1 ( RDEN $end
$var reg 16 ) WRDAT [15:0] $end
$var reg 1 * WRDV $end
$var integer 32 + idx [31:0] $end
$scope module uut $end
$var wire 1 & LCLK $end
$var wire 1 ' RCLK $end
$var wire 1 ( RDEN $end
$var wire 16 , WRDAT [15:0] $end
$var wire 1 * WRDV $end
$var wire 6 - rd_ptr_grey [5:0] $end
$var wire 6 . wr_ptr_grey [5:0] $end
$var parameter 32 / depth $end
$var parameter 32 0 width $end
$var reg 1 # E $end
$var reg 1 " F $end
$var reg 16 1 RDDAT [15:0] $end
$var reg 6 2 rd_ptr_bin [5:0] $end
$var reg 6 3 rd_ptr_grey_sync_1 [5:0] $end
$var reg 6 4 rd_ptr_grey_sync_2 [5:0] $end
$var reg 6 5 wr_ptr_bin [5:0] $end
$var reg 6 6 wr_ptr_grey_sync_1 [5:0] $end
$var reg 6 7 wr_ptr_grey_sync_2 [5:0] $end
$upscope $end
$upscope $end
$enddefinitions $end
$comment Show the parameter values. $end
$dumpall
b10000 0
b100000 /
b10000 %
b100000 $
$end
#0
$dumpvars
bx 7
bx 6
b0 5
bx 4
bx 3
b0 2
bx 1
b0 .
b0 -
b0 ,
bx +
0*
b0 )
0(
0'
0&
x#
x"
bx !
$end
#5
b0 3
1&
#7
b0 6
1'
#10
0&
#14
0'
#15
0"
b0 4
1&
#20
0&
1*
b1 )
b1 ,
b1 +
#21
1#
b0 7
1'
#25
b1 .
b1 5
1&
#28
0'
#30
0&
0*
#35
b1 6
1&
1'
#40
0&
1*
b10 )
b10 ,
b10 +
#42
0'
#45
b11 .
b10 5
1&
#49
0#
b1 7
b11 6
1'
#50
0&
0*
#55
1&
#56
0'
#60
0&
1*
b11 )
b11 ,
b11 +
#63
b11 7
1'
#65
b10 .
b11 5
1&
#70
0&
0'
0*
#75
1&
#77
b10 6
1'
#80
0&
1*
b100 )
b100 ,
b100 +
#84
0'
#85
b110 .
b100 5
1&
#90
0&
0*
#91
b10 7
b110 6
1'
#95
1&
#98
0'
#100
0&
1*
b101 )
b101 ,
b101 +
#105
b111 .
b101 5
b110 7
1&
1'
#110
0&
0*
#112
0'
#115
1&
#119
b111 6
1'
#120
0&
1*
b110 )
b110 ,
b110 +
#125
b101 .
b110 5
1&
#126
0'
#130
0&
0*
#133
b111 7
b101 6
1'
#135
1&
#140
0&
0'
1*
b111 )
b111 ,
b111 +
#145
b100 .
b111 5
1&
#147
b101 7
b100 6
1'
#150
0&
0*
#154
0'
#155
1&
#160
0&
1*
b1000 )
b1000 ,
b1000 +
#161
b100 7
1'
#165
b1100 .
b1000 5
1&
#168
0'
#170
0&
0*
#175
b1100 6
1&
1'
#180
0&
1*
b1001 )
b1001 ,
b1001 +
#182
0'
#185
b1101 .
b1001 5
1&
#189
b1100 7
b1101 6
1'
#190
0&
0*
#195
1&
#196
0'
#200
0&
1*
b1010 )
b1010 ,
b1010 +
#203
b1101 7
1'
#205
b1111 .
b1010 5
1&
#210
0&
0'
0*
#215
1&
#217
b1111 6
1'
#220
0&
1*
b1011 )
b1011 ,
b1011 +
#224
0'
#225
b1110 .
b1011 5
1&
#230
0&
0*
#231
b1111 7
b1110 6
1'
#235
1&
#238
0'
#240
0&
1*
b1100 )
b1100 ,
b1100 +
#245
b1010 .
b1100 5
b1110 7
1&
1'
#250
0&
0*
#252
0'
#255
1&
#259
b1010 6
1'
#260
0&
1*
b1101 )
b1101 ,
b1101 +
#265
b1011 .
b1101 5
1&
#266
0'
#270
0&
0*
#273
b1010 7
b1011 6
1'
#275
1&
#280
0&
0'
1*
b1110 )
b1110 ,
b1110 +
#285
b1001 .
b1110 5
1&
#287
b1011 7
b1001 6
1'
#290
0&
0*
#294
0'
#295
1&
#300
0&
1*
b1111 )
b1111 ,
b1111 +
#301
b1001 7
1'
#305
b1000 .
b1111 5
1&
#308
0'
#310
0&
0*
#315
b1000 6
1&
1'
#320
0&
1*
b10000 )
b10000 ,
b10000 +
#322
0'
#325
b11000 .
b10000 5
1&
#329
b1000 7
b11000 6
1'
#330
0&
0*
#335
1&
#336
0'
#340
0&
1*
b10001 )
b10001 ,
b10001 +
#343
b11000 7
1'
#345
b11001 .
b10001 5
1&
#350
0&
0'
0*
#355
1&
#357
b11001 6
1'
#360
0&
1*
b10010 )
b10010 ,
b10010 +
#364
0'
#365
b11011 .
b10010 5
1&
#370
0&
0*
#371
b11001 7
b11011 6
1'
#375
1&
#378
0'
#380
0&
1*
b10011 )
b10011 ,
b10011 +
#385
b11010 .
b10011 5
b11011 7
1&
1'
#390
0&
0*
#392
0'
#395
1&
#399
b11010 6
1'
#400
0&
1*
b10100 )
b10100 ,
b10100 +
#405
b11110 .
b10100 5
1&
#406
0'
#410
0&
0*
#413
b11010 7
b11110 6
1'
#415
1&
#420
0&
0'
1*
b10101 )
b10101 ,
b10101 +
#425
b11111 .
b10101 5
1&
#427
b11110 7
b11111 6
1'
#430
0&
0*
#434
0'
#435
1&
#440
0&
1*
b10110 )
b10110 ,
b10110 +
#441
b11111 7
1'
#445
b11101 .
b10110 5
1&
#448
0'
#450
0&
0*
#455
b11101 6
1&
1'
#460
0&
1*
b10111 )
b10111 ,
b10111 +
#462
0'
#465
b11100 .
b10111 5
1&
#469
b11101 7
b11100 6
1'
#470
0&
0*
#475
1&
#476
0'
#480
0&
1*
b11000 )
b11000 ,
b11000 +
#483
b11100 7
1'
#485
b10100 .
b11000 5
1&
#490
0&
0'
0*
#495
1&
#497
b10100 6
1'
#500
0&
1*
b11001 )
b11001 ,
b11001 +
#504
0'
#505
b10101 .
b11001 5
1&
#510
0&
0*
#511
b10100 7
b10101 6
1'
#515
1&
#518
0'
#520
0&
1*
b11010 )
b11010 ,
b11010 +
#525
b10111 .
b11010 5
b10101 7
1&
1'
#530
0&
0*
#532
0'
#535
1&
#539
b10111 6
1'
#540
0&
1*
b11011 )
b11011 ,
b11011 +
#545
b10110 .
b11011 5
1&
#546
0'
#550
0&
0*
#553
b10111 7
b10110 6
1'
#555
1&
#560
0&
0'
1*
b11100 )
b11100 ,
b11100 +
#565
b10010 .
b11100 5
1&
#567
b10110 7
b10010 6
1'
#570
0&
0*
#574
0'
#575
1&
#580
0&
1*
b11101 )
b11101 ,
b11101 +
#581
b10010 7
1'
#585
b10011 .
b11101 5
1&
#588
0'
#590
0&
0*
#595
b10011 6
1&
1'
#600
0&
1*
b11110 )
b11110 ,
b11110 +
#602
0'
#605
b10001 .
b11110 5
1&
#609
b10011 7
b10001 6
1'
#610
0&
0*
#615
1&
#616
0'
#620
0&
1*
b11111 )
b11111 ,
b11111 +
#623
b10001 7
1'
#625
b10000 .
b11111 5
1&
#630
0&
0'
0*
#635
1&
#637
b10000 6
1'
#640
0&
1*
b100000 )
b100000 ,
b100000 +
#644
0'
#645
1"
b110000 .
b100000 5
1&
#650
0&
0*
#651
b10000 7
b110000 6
1'
#655
1&
#658
0'
#660
0&
1*
b100001 )
b100001 ,
b100001 +
#665
b110000 7
1&
1'
#670
0&
0*
#672
0'
#675
1&
#679
1'
#680
0&
1*
b100010 )
b100010 ,
b100010 +
#685
1&
#686
0'
#690
0&
0*
#693
1'
#695
1&
#700
0&
0'
1*
b100011 )
b100011 ,
b100011 +
#705
1&
#707
1'
#710
0&
0*
#714
0'
#715
1&
#720
0&
b100100 +
#721
1'
#725
1&
#728
0'
#730
0&
#735
1&
1'
#740
0&
#742
0'
#745
1&
#749
1'
#750
0&
#755
1&
#756
0'
#760
0&
#763
1'
#765
1&
#770
0&
0'
1(
b0 +
#775
1&
#777
b1 -
b1 2
b1 !
b1 1
1'
#780
0&
#784
0'
0(
#785
b1 3
1&
#790
0&
#791
1'
#795
0"
b1 4
1&
#798
0'
1(
b1 +
#800
0&
#805
b11 -
b10 2
b10 !
b10 1
1&
1'
#810
0&
#812
0'
0(
#815
b11 3
1&
#819
1'
#820
0&
#825
b11 4
1&
#826
0'
1(
b10 +
#830
0&
#833
b10 -
b11 2
b11 !
b11 1
1'
#835
b10 3
1&
#840
0&
0'
0(
#845
b10 4
1&
#847
1'
#850
0&
#854
0'
1(
b11 +
#855
1&
#860
0&
#861
b110 -
b100 2
b100 !
b100 1
1'
#865
b110 3
1&
#868
0'
0(
#870
0&
#875
b110 4
1&
1'
#880
0&
#882
0'
1(
b100 +
#885
1&
#889
b111 -
b101 2
b101 !
b101 1
1'
#890
0&
#895
b111 3
1&
#896
0'
0(
#900
0&
#903
1'
#905
b111 4
1&
#910
0&
0'
b101 +
#915
1&
#917
1'
#920
0&
#924
0'
#925
1&
#930
0&
#931
1'
#935
1&
#938
0'
#940
0&
#945
1&
1'
#950
0&
#952
0'
#955
1&
#959
1'
#960
0&
1*
b1010101010101010 )
b1010101010101010 ,
#965
b110001 .
b100001 5
1&
#966
0'
#970
0&
0*
#973
b110001 6
1'
#975
1&
#980
0&
0'
1*
b1011101110111011 )
b1011101110111011 ,
#985
b110011 .
b100010 5
1&
#987
b110001 7
b110011 6
1'
#990
0&
0*
#994
0'
#995
1&
#1000
0&
#1001
b110011 7
1'
